GetTransTool/GetCDSLongestFromGTF.py
GetTransTool/GetCDSLongestFromGencode.py
GetTransTool/GetLongestTransFromGTF.py
GetTransTool/GetLongestTransFromGencode.py
GetTransTool/__init__.py
GetTransTool-0.0.7.dist-info/LICENSE
GetTransTool-0.0.7.dist-info/METADATA
GetTransTool-0.0.7.dist-info/WHEEL
GetTransTool-0.0.7.dist-info/entry_points.txt
GetTransTool-0.0.7.dist-info/top_level.txt
GetTransTool-0.0.7.dist-info/RECORD
