Metadata-Version: 2.1
Name: GetTransTool
Version: 0.0.7
Summary: Extract longest transcript or longest CDS transcript from GTF annotation file or gencode transcripts fasta file.
Home-page: https://github.com/junjunlab/GetTransTool
Author: laojunjun
Author-email: 3219030654@stu.cpu.edu.cn
License: UNKNOWN
Project-URL: Bug Tracker, https://github.com/junjunlab/GetTransTool/issues
Platform: UNKNOWN
Classifier: Programming Language :: Python :: 3
Classifier: License :: OSI Approved :: MIT License
Classifier: Operating System :: OS Independent
Requires-Python: >=3.6
License-File: LICENSE
